{
  "code": 0,
  "data": {
    "list": [
      {
        "alias": "",
        "auto_update": true,
        "check_time": null,
        "check_time_label": null,
        "connect_status": false,
        "create_time": "2023-06-04 19:32:07",
        "create_time_label": "2023-06-04",
        "domain": "www.apple.com",
        "domain_auto_update": true,
        "domain_check_time": "2023-06-07 16:49:50",
        "domain_expire_days": 257,
        "domain_expire_monitor": true,
        "domain_expire_time": "2024-02-20 05:00:00",
        "domain_start_time": "1987-02-19 05:00:00",
        "domain_url": "https://www.apple.com",
        "expire_days": 0,
        "expire_time": null,
        "group_id": 0,
        "id": 7,
        "ip": "",
        "ip_auto_update": true,
        "ip_check_time": null,
        "is_monitor": true,
        "notify_status": true,
        "port": 444,
        "real_time_domain_expire_days": 257,
        "real_time_expire_days": null,
        "real_time_ssl_expire_days": null,
        "real_time_ssl_total_days": 0,
        "start_time": null,
        "total_days": 0,
        "update_time": "2023-06-07 16:51:05",
        "update_time_label": "44\u5206\u949f\u524d",
        "user_id": 1
      },
      {
        "alias": "",
        "auto_update": true,
        "check_time": null,
        "check_time_label": null,
        "connect_status": false,
        "create_time": "2023-06-04 19:32:01",
        "create_time_label": "2023-06-04",
        "domain": "www.toutiao.com",
        "domain_auto_update": true,
        "domain_check_time": "2023-06-07 16:30:02",
        "domain_expire_days": 1349,
        "domain_expire_monitor": true,
        "domain_expire_time": "2027-02-16 06:00:15",
        "domain_start_time": "2004-02-16 06:00:15",
        "domain_url": "https://www.toutiao.com",
        "expire_days": 0,
        "expire_time": null,
        "group_id": 0,
        "id": 6,
        "ip": "",
        "ip_auto_update": true,
        "ip_check_time": null,
        "is_monitor": true,
        "notify_status": true,
        "port": 444,
        "real_time_domain_expire_days": 1349,
        "real_time_expire_days": null,
        "real_time_ssl_expire_days": null,
        "real_time_ssl_total_days": 0,
        "start_time": null,
        "total_days": 0,
        "update_time": "2023-06-07 16:49:50",
        "update_time_label": "45\u5206\u949f\u524d",
        "user_id": 1
      },
      {
        "alias": "\u660e\u5929\u6536\u8d2d",
        "auto_update": true,
        "check_time": null,
        "check_time_label": null,
        "connect_status": true,
        "create_time": "2023-06-04 18:32:50",
        "create_time_label": "2023-06-04",
        "domain": "www.baidu.com",
        "domain_auto_update": true,
        "domain_check_time": "2023-06-07 16:30:00",
        "domain_expire_days": 1221,
        "domain_expire_monitor": true,
        "domain_expire_time": "2026-10-11 11:05:17",
        "domain_start_time": "1999-10-11 11:05:17",
        "domain_url": "https://www.baidu.com",
        "expire_days": 59,
        "expire_time": "2023-08-06 13:16:01",
        "group_id": 1,
        "id": 1,
        "ip": "",
        "ip_auto_update": true,
        "ip_check_time": null,
        "is_monitor": true,
        "notify_status": true,
        "port": 443,
        "real_time_domain_expire_days": 1221,
        "real_time_expire_days": 59,
        "real_time_ssl_expire_days": 59,
        "real_time_ssl_total_days": 396,
        "start_time": "2022-07-05 13:16:02",
        "total_days": 0,
        "update_time": "2023-06-07 16:30:00",
        "update_time_label": "1\u5c0f\u65f6\u524d",
        "user_id": 1
      },
      {
        "alias": "",
        "auto_update": true,
        "check_time": null,
        "check_time_label": null,
        "connect_status": true,
        "create_time": "2023-06-04 19:32:13",
        "create_time_label": "2023-06-04",
        "domain": "www.pconline.com.cn",
        "domain_auto_update": true,
        "domain_check_time": "2023-06-07 16:51:05",
        "domain_expire_days": 2839,
        "domain_expire_monitor": true,
        "domain_expire_time": "2031-03-17 00:00:00",
        "domain_start_time": "1999-03-17 00:00:00",
        "domain_url": "https://www.pconline.com.cn",
        "expire_days": 123,
        "expire_time": "2023-10-09 14:28:39",
        "group_id": 0,
        "id": 8,
        "ip": "",
        "ip_auto_update": true,
        "ip_check_time": null,
        "is_monitor": true,
        "notify_status": true,
        "port": 443,
        "real_time_domain_expire_days": 2839,
        "real_time_expire_days": 123,
        "real_time_ssl_expire_days": 123,
        "real_time_ssl_total_days": 396,
        "start_time": "2022-09-07 14:28:40",
        "total_days": 0,
        "update_time": "2023-06-07 16:51:06",
        "update_time_label": "44\u5206\u949f\u524d",
        "user_id": 1
      },
      {
        "alias": "",
        "auto_update": true,
        "check_time": null,
        "check_time_label": null,
        "connect_status": true,
        "create_time": "2023-06-04 18:41:46",
        "create_time_label": "2023-06-04",
        "domain": "www.jd.com",
        "domain_auto_update": true,
        "domain_check_time": "2023-06-07 16:30:00",
        "domain_expire_days": 1735,
        "domain_expire_monitor": true,
        "domain_expire_time": "2028-03-08 05:17:11",
        "domain_start_time": "1992-09-29 04:00:00",
        "domain_url": "https://www.jd.com",
        "expire_days": 164,
        "expire_time": "2023-11-19 14:52:17",
        "group_id": 2,
        "id": 2,
        "ip": "",
        "ip_auto_update": true,
        "ip_check_time": null,
        "is_monitor": true,
        "notify_status": true,
        "port": 443,
        "real_time_domain_expire_days": 1735,
        "real_time_expire_days": 164,
        "real_time_ssl_expire_days": 164,
        "real_time_ssl_total_days": 396,
        "start_time": "2022-10-18 15:17:10",
        "total_days": 0,
        "update_time": "2023-06-07 16:30:00",
        "update_time_label": "1\u5c0f\u65f6\u524d",
        "user_id": 1
      },
      {
        "alias": "",
        "auto_update": true,
        "check_time": null,
        "check_time_label": null,
        "connect_status": true,
        "create_time": "2023-06-04 19:32:31",
        "create_time_label": "2023-06-04",
        "domain": "www.csdn.net",
        "domain_auto_update": true,
        "domain_check_time": "2023-06-07 16:51:06",
        "domain_expire_days": 277,
        "domain_expire_monitor": true,
        "domain_expire_time": "2024-03-11 04:00:00",
        "domain_start_time": "1999-03-11 05:00:00",
        "domain_url": "https://www.csdn.net",
        "expire_days": 177,
        "expire_time": "2023-12-02 07:59:59",
        "group_id": 0,
        "id": 9,
        "ip": "",
        "ip_auto_update": true,
        "ip_check_time": null,
        "is_monitor": true,
        "notify_status": true,
        "port": 443,
        "real_time_domain_expire_days": 277,
        "real_time_expire_days": 177,
        "real_time_ssl_expire_days": 177,
        "real_time_ssl_total_days": 368,
        "start_time": "2022-11-28 08:00:00",
        "total_days": 0,
        "update_time": "2023-06-07 16:51:06",
        "update_time_label": "44\u5206\u949f\u524d",
        "user_id": 1
      },
      {
        "alias": "",
        "auto_update": true,
        "check_time": null,
        "check_time_label": null,
        "connect_status": true,
        "create_time": "2023-06-04 19:31:06",
        "create_time_label": "2023-06-04",
        "domain": "www.qq.com",
        "domain_auto_update": true,
        "domain_check_time": "2023-06-07 16:30:00",
        "domain_expire_days": 2971,
        "domain_expire_monitor": true,
        "domain_expire_time": "2031-07-27 02:09:19",
        "domain_start_time": "1995-05-04 04:00:00",
        "domain_url": "https://www.qq.com",
        "expire_days": 300,
        "expire_time": "2024-04-03 07:59:59",
        "group_id": 0,
        "id": 4,
        "ip": "",
        "ip_auto_update": true,
        "ip_check_time": null,
        "is_monitor": true,
        "notify_status": true,
        "port": 443,
        "real_time_domain_expire_days": 2971,
        "real_time_expire_days": 300,
        "real_time_ssl_expire_days": 300,
        "real_time_ssl_total_days": 367,
        "start_time": "2023-04-01 08:00:00",
        "total_days": 0,
        "update_time": "2023-06-07 16:30:01",
        "update_time_label": "1\u5c0f\u65f6\u524d",
        "user_id": 1
      },
      {
        "alias": "",
        "auto_update": true,
        "check_time": null,
        "check_time_label": null,
        "connect_status": true,
        "create_time": "2023-06-04 19:31:34",
        "create_time_label": "2023-06-04",
        "domain": "www.163.com",
        "domain_auto_update": true,
        "domain_check_time": "2023-06-07 16:30:01",
        "domain_expire_days": 1194,
        "domain_expire_monitor": true,
        "domain_expire_time": "2026-09-14 04:00:00",
        "domain_start_time": "1997-09-15 04:00:00",
        "domain_url": "https://www.163.com",
        "expire_days": 320,
        "expire_time": "2024-04-23 07:59:59",
        "group_id": 0,
        "id": 5,
        "ip": "",
        "ip_auto_update": true,
        "ip_check_time": null,
        "is_monitor": true,
        "notify_status": true,
        "port": 443,
        "real_time_domain_expire_days": 1194,
        "real_time_expire_days": 320,
        "real_time_ssl_expire_days": 320,
        "real_time_ssl_total_days": 396,
        "start_time": "2023-03-23 08:00:00",
        "total_days": 0,
        "update_time": "2023-06-07 16:30:02",
        "update_time_label": "1\u5c0f\u65f6\u524d",
        "user_id": 1
      },
      {
        "alias": "",
        "auto_update": true,
        "check_time": null,
        "check_time_label": null,
        "connect_status": true,
        "create_time": "2023-06-04 19:30:58",
        "create_time_label": "2023-06-04",
        "domain": "www.360.com",
        "domain_auto_update": true,
        "domain_check_time": "2023-06-07 16:30:00",
        "domain_expire_days": 273,
        "domain_expire_monitor": true,
        "domain_expire_time": "2024-03-07 11:54:37",
        "domain_start_time": "2000-03-07 11:54:37",
        "domain_url": "https://www.360.com",
        "expire_days": 321,
        "expire_time": "2024-04-24 07:59:59",
        "group_id": 0,
        "id": 3,
        "ip": "",
        "ip_auto_update": true,
        "ip_check_time": null,
        "is_monitor": true,
        "notify_status": true,
        "port": 443,
        "real_time_domain_expire_days": 273,
        "real_time_expire_days": 321,
        "real_time_ssl_expire_days": 321,
        "real_time_ssl_total_days": 365,
        "start_time": "2023-04-24 08:00:00",
        "total_days": 0,
        "update_time": "2023-06-07 16:30:00",
        "update_time_label": "1\u5c0f\u65f6\u524d",
        "user_id": 1
      }
    ],
    "total": 10
  },
  "msg": "success"
}
